[
    {
        "name": "Donut Plains 3",
        "access_rules": [
            ""
        ],
        "visibility_rules": [
            ""
        ],
        "children": [
            {
                "sections": [
                    {
                        "visibility_rules": [
                            ""
                        ],
                        "name": "Normal Exit",
                        "access_rules": [
                            ""
                        ],
                        "chest_unopened_img": "images/checks/goal_sphere_disabled.png",
                        "chest_opened_img": "images/checks/goal_sphere.png",
                        "item_count": 1
                    }
                ],
                "name": "Donut Plains 3 - Goal",
                "map_locations": [
                    {
                        "map": "dp3_main",
                        "x": 744,
                        "y": 1240
                    }
                ]
            },
            {
                "sections": [
                    {
                        "visibility_rules": [
                            "dragon_coin_checks"
                        ],
                        "name": "Dragon Coins",
                        "access_rules": [
                            "spin_jump, powerup_1, climb",
                            "yoshi",
                            "powerup_3, run"
                        ],
                        "chest_unopened_img": "images/checks/dragon_coin_disabled.png",
                        "chest_opened_img": "images/checks/dragon_coin.png",
                        "clear_as_group": true,
                        "item_count": 1
                    }
                ],
                "name": "Donut Plains 3 - Dragon coin",
                "map_locations": [
                    {
                        "map": "dp3_main",
                        "x": 744,
                        "y": 240
                    },
                    {
                        "map": "dp3_main",
                        "x": 1816,
                        "y": 80
                    },
                    {
                        "map": "dp3_main",
                        "x": 584,
                        "y": 656
                    },
                    {
                        "map": "dp3_main",
                        "x": 1544,
                        "y": 672
                    },
                    {
                        "map": "dp3_main",
                        "x": 2040,
                        "y": 784
                    }
                ]
            },
            {
                "sections": [
                    {
                        "visibility_rules": [
                            "bonus_block_checks"
                        ],
                        "name": "1-Up from Bonus Block",
                        "access_rules": [
                            ""
                        ],
                        "chest_unopened_img": "images/checks/bonus_disabled.png",
                        "chest_opened_img": "images/checks/bonus.png",
                        "item_count": 1
                    }
                ],
                "name": "Donut Plains 3 - Prize from bonus block",
                "map_locations": [
                    {
                        "map": "dp3_main",
                        "x": 600,
                        "y": 1096
                    }
                ]
            },
            {
                "name": "Donut Plains 3 - Blocksanity - Green Switch Palace Block #1",
                "sections": [
                    {
                        "name": "Green Switch Palace Block #1",
                        "access_rules": [
                            "gsp"
                        ],
                        "visibility_rules": [
                            "blocksanity"
                        ],
                        "chest_unopened_img": "images/checks/blocksanity_disabled.png",
                        "chest_opened_img": "images/checks/blocksanity.png",
                        "item_count": 1
                    }
                ],
                "map_locations": [
                    {
                        "map": "dp3_main",
                        "x": 440,
                        "y": 232
                    }
                ]
            },
            {
                "name": "Donut Plains 3 - Blocksanity - Coin Block #1",
                "sections": [
                    {
                        "name": "Coin Block #1",
                        "access_rules": [
                            ""
                        ],
                        "visibility_rules": [
                            "blocksanity"
                        ],
                        "chest_unopened_img": "images/checks/blocksanity_disabled.png",
                        "chest_opened_img": "images/checks/blocksanity.png",
                        "item_count": 1
                    }
                ],
                "map_locations": [
                    {
                        "map": "dp3_main",
                        "x": 1112,
                        "y": 248
                    }
                ]
            },
            {
                "name": "Donut Plains 3 - Blocksanity - Coin Block #2",
                "sections": [
                    {
                        "name": "Coin Block #2",
                        "access_rules": [
                            ""
                        ],
                        "visibility_rules": [
                            "blocksanity"
                        ],
                        "chest_unopened_img": "images/checks/blocksanity_disabled.png",
                        "chest_opened_img": "images/checks/blocksanity.png",
                        "item_count": 1
                    }
                ],
                "map_locations": [
                    {
                        "map": "dp3_main",
                        "x": 1160,
                        "y": 248
                    }
                ]
            },
            {
                "name": "Donut Plains 3 - Blocksanity - Vine Block #1",
                "sections": [
                    {
                        "name": "Vine Block #1",
                        "access_rules": [
                            "powerup_1, spin_jump"
                        ],
                        "visibility_rules": [
                            "blocksanity"
                        ],
                        "chest_unopened_img": "images/checks/blocksanity_disabled.png",
                        "chest_opened_img": "images/checks/blocksanity.png",
                        "item_count": 1
                    }
                ],
                "map_locations": [
                    {
                        "map": "dp3_main",
                        "x": 1256,
                        "y": 312
                    }
                ]
            },
            {
                "name": "Donut Plains 3 - Blocksanity - Powerup Block #1",
                "sections": [
                    {
                        "name": "Powerup Block #1",
                        "access_rules": [
                            ""
                        ],
                        "visibility_rules": [
                            "blocksanity"
                        ],
                        "chest_unopened_img": "images/checks/blocksanity_disabled.png",
                        "chest_opened_img": "images/checks/blocksanity.png",
                        "item_count": 1
                    }
                ],
                "map_locations": [
                    {
                        "map": "dp3_main",
                        "x": 984,
                        "y": 760
                    }
                ]
            },
            {
                "name": "Donut Plains 3 - Blocksanity - Bonus Block #1",
                "sections": [
                    {
                        "name": "Bonus Block #1",
                        "access_rules": [
                            ""
                        ],
                        "visibility_rules": [
                            "blocksanity"
                        ],
                        "chest_unopened_img": "images/checks/blocksanity_disabled.png",
                        "chest_opened_img": "images/checks/blocksanity.png",
                        "item_count": 1
                    }
                ],
                "map_locations": [
                    {
                        "map": "dp3_main",
                        "x": 600,
                        "y": 1112
                    }
                ]
            }
        ]
    }
]